sqfa/__init__.py
sqfa/_optim.py
sqfa/constraints.py
sqfa/distances.py
sqfa/linalg.py
sqfa/model.py
sqfa/statistics.py
sqfa/plot/__init__.py
sqfa/plot/_data_wrangle.py
sqfa/plot/colors.py
sqfa/plot/data.py
sqfa/plot/ellipses.py
sqfa-0.2.0.dist-info/METADATA
sqfa-0.2.0.dist-info/WHEEL
sqfa-0.2.0.dist-info/licenses/LICENSE
sqfa-0.2.0.dist-info/RECORD
