Metadata-Version: 2.4
Name: sqfa
Version: 0.2.0
Summary: Supervised Quadratic Feature Analysis: Task specific second order feature extraction
Project-URL: Repository, https://github.com/dherrera1911/sqfa
Project-URL: Source, https://github.com/dherrera1911/sqfa
Project-URL: Bug Reports, https://github.com/dherrera1911/sqfa/issues
Project-URL: Documentation, https://sqfa.readthedocs.io/en/latest/
Author-email: Daniel Herrera-Esposito <dherrera1911@gmail.com>
License: MIT License
License-File: LICENSE
Keywords: covariance matrices,dimensionality reduction,information geometry,machine learning,manifold,pytorch,second moments
Classifier: Development Status :: 4 - Beta
Classifier: Intended Audience :: Science/Research
Classifier: License :: OSI Approved :: MIT License
Classifier: Programming Language :: Python :: 3.9
Classifier: Programming Language :: Python :: 3.10
Classifier: Programming Language :: Python :: 3.11
Classifier: Programming Language :: Python :: 3.12
Requires-Python: >=3.8
Requires-Dist: matplotlib
Requires-Dist: numpy>=1.1
Requires-Dist: torch>=1.8
Requires-Dist: tqdm>=4.29
Provides-Extra: dev
Requires-Dist: pytest-cov; extra == 'dev'
Requires-Dist: pytest-xdist; extra == 'dev'
Requires-Dist: pytest>=5.1.2; extra == 'dev'
Requires-Dist: scikit-learn; extra == 'dev'
Requires-Dist: torchvision; extra == 'dev'
Provides-Extra: docs
Requires-Dist: docutils<0.21,>=0.18.1; extra == 'docs'
Requires-Dist: ipython; extra == 'docs'
Requires-Dist: myst-nb; extra == 'docs'
Requires-Dist: nbsphinx; extra == 'docs'
Requires-Dist: nbsphinx-link; extra == 'docs'
Requires-Dist: numpydoc; extra == 'docs'
Requires-Dist: scikit-learn; extra == 'docs'
Requires-Dist: sphinx; extra == 'docs'
Requires-Dist: sphinx-autodoc-typehints; extra == 'docs'
Requires-Dist: sphinx-copybutton; extra == 'docs'
Requires-Dist: sphinx-inline-tabs; extra == 'docs'
Requires-Dist: sphinx-rtd-theme>=1.3.0rc1; extra == 'docs'
Requires-Dist: sphinxcontrib-apidoc; extra == 'docs'
Requires-Dist: sphinxemoji; extra == 'docs'
Requires-Dist: torchvision; extra == 'docs'
Provides-Extra: test
Requires-Dist: pytest-cov; extra == 'test'
Requires-Dist: pytest-xdist; extra == 'test'
Requires-Dist: pytest>=5.1.2; extra == 'test'
Requires-Dist: scipy; extra == 'test'
